README.md
setup.py
Forecast_Checker/__init__.py
Forecast_Checker.egg-info/PKG-INFO
Forecast_Checker.egg-info/SOURCES.txt
Forecast_Checker.egg-info/dependency_links.txt
Forecast_Checker.egg-info/requires.txt
Forecast_Checker.egg-info/top_level.txt