Metadata-Version: 1.0
Name: Forecast-Checker
Version: 0.1
Summary: Evaluate Forecast model performance vs step size
Home-page: https://github.com/dstarkey23/Forecast_Checker
Author: David Starkey
Author-email: davidstarkey29@gmail.com
License: Apache
Platform: UNKNOWN
